seodo/__init__.py
seodo/main.py
seodo-0.0.13.dist-info/entry_points.txt
seodo-0.0.13.dist-info/WHEEL
seodo-0.0.13.dist-info/METADATA
seodo-0.0.13.dist-info/RECORD
