Metadata-Version: 2.1
Name: seodo
Version: 0.0.13
Summary: Seo.do terminal client
Author: Seo Do
Requires-Python: >=3.5,<4.0
Classifier: Programming Language :: Python :: 3
Classifier: Programming Language :: Python :: 3.5
Classifier: Programming Language :: Python :: 3.6
Classifier: Programming Language :: Python :: 3.7
Classifier: Programming Language :: Python :: 3.8
Requires-Dist: certifi (==2020.4.5.1)
Requires-Dist: chardet (==3.0.4)
Requires-Dist: click (==7.1.1)
Requires-Dist: future (==0.18.2)
Requires-Dist: requests (==2.23.0)
Requires-Dist: tabulate (==0.8.7)
Requires-Dist: typer[all] (>=0.1.1,<0.2.0)
